facture/__init__.py
facture/__version__.py
facture/db.py
facture/exceptions.py
facture/log.py
facture/registry.py
facture/schema.py
facture/utils.py
facture/controller/__init__.py
facture/controller/base.py
facture/controller/decorators.py
facture/controller/injector.py
facture/core/__init__.py
facture/core/app.py
facture/core/component.py
facture/core/error.py
facture/core/manager.py
facture/core/package.py
facture/core/settings.py
facture/service/__init__.py
facture/service/base.py
facture/service/db.py
facture/service/http.py
facture-0.2.1.dist-info/DESCRIPTION.rst
facture-0.2.1.dist-info/LICENSE.txt
facture-0.2.1.dist-info/METADATA
facture-0.2.1.dist-info/RECORD
facture-0.2.1.dist-info/WHEEL
facture-0.2.1.dist-info/entry_points.txt
facture-0.2.1.dist-info/metadata.json
facture-0.2.1.dist-info/top_level.txt
