Metadata-Version: 2.0
Name: facture
Version: 0.2.1
Summary: Framework for building Web APIs using asyncio
Home-page: https://github.com/rbw/facture
Author: Robert Wikman
Author-email: rbw@vault13.org
License: BSD-2
Platform: UNKNOWN
Classifier: Programming Language :: Python
Classifier: Programming Language :: Python :: 3.6
Classifier: Programming Language :: Python :: 3.7
Classifier: Programming Language :: Python :: Implementation :: CPython
Requires-Python: >=3.6
Requires-Dist: sanic (>=18.12.0)
Requires-Dist: aiohttp (>=4.0.0a0)
Requires-Dist: aiopg (>=0.16.0)
Requires-Dist: psycopg2-binary (>=2.7.7)
Requires-Dist: marshmallow (>=3.0.0rc4)
Requires-Dist: peewee-async (>=0.6.0a0)
Requires-Dist: peewee (>=3.9.2)
Requires-Dist: apispec (>=1.0.0)
Requires-Dist: ujson (>=1.35)
Requires-Dist: uvloop (>=0.12.1)
